jupyter_operator/__init__.py
jupyter_operator/__main__.py
jupyter_operator/_version.py
jupyter_operator/handlers.py
jupyter_operator/serverapplication.py
jupyter_operator/echo/__init__.py
jupyter_operator/echo/handler.py
jupyter_operator/pong/__init__.py
jupyter_operator/pong/handler.py
jupyter_operator/proxy/__init__.py
jupyter_operator/proxy/handler.py
jupyter_operator/relay/__init__.py
jupyter_operator/relay/handler.py
jupyter_operator/static/README.md
jupyter_operator/static/main.jupyter-operator.js
jupyter_operator/templates/index.html
jupyter_operator/tests/__init__.py
jupyter_operator/tests/test_handlers.py
jupyter_operator-0.0.5.data/data/etc/jupyter/jupyter_notebook_config.d/jupyter_operator.json
jupyter_operator-0.0.5.data/data/etc/jupyter/jupyter_server_config.d/jupyter_operator.json
jupyter_operator-0.0.5.data/data/share/jupyter/labextensions/@datalayer/jupyter-operator/build_log.json
jupyter_operator-0.0.5.data/data/share/jupyter/labextensions/@datalayer/jupyter-operator/package.json
jupyter_operator-0.0.5.data/data/share/jupyter/labextensions/@datalayer/jupyter-operator/schemas/@datalayer/jupyter-operator/package.json.orig
jupyter_operator-0.0.5.data/data/share/jupyter/labextensions/@datalayer/jupyter-operator/schemas/@datalayer/jupyter-operator/plugin.json
jupyter_operator-0.0.5.data/data/share/jupyter/labextensions/@datalayer/jupyter-operator/static/icons_react_index_esm_js.65493c25dd332aaf6b10.js
jupyter_operator-0.0.5.data/data/share/jupyter/labextensions/@datalayer/jupyter-operator/static/icons_react_index_esm_js.65493c25dd332aaf6b10.js.map
jupyter_operator-0.0.5.data/data/share/jupyter/labextensions/@datalayer/jupyter-operator/static/lib_index_js.f1f1be6235af06d15eb7.js
jupyter_operator-0.0.5.data/data/share/jupyter/labextensions/@datalayer/jupyter-operator/static/lib_index_js.f1f1be6235af06d15eb7.js.map
jupyter_operator-0.0.5.dist-info/METADATA
jupyter_operator-0.0.5.dist-info/WHEEL
jupyter_operator-0.0.5.dist-info/licenses/LICENSE
jupyter_operator-0.0.5.dist-info/RECORD
